Workbook

Sheet 税額表
A1: 月額給与（円以上） | B1: 源泉所得税額（乙欄）
A2: 0 | B2: 0
A3: 68000 | B3: 3200
A4: 75000 | B4: 3500
A5: 80000 | B5: 3800
A6: 88000 | B6: 4200
A7: 93000 | B7: 4700
A8: 98000 | B8: 5200
A9: 103000 | B9: 5700
A10: 108000 | B10: 6200
A11: 114000 | B11: 7000
A12: 119000 | B12: 7500
A13: 124000 | B13: 8000
... A74: 925000 | B74: 100400

Sheet 1月
A1: 2026年 1月 アルバイト勤怠表
A2: 従業員名 | C2: 仲本 正 | G2: 時 給 | I2: 1300 | L2: （税区分：乙欄 雇用保険なし）
A3: 日 付 | B3: 曜 日 | C3: 勤務 開始時刻 | D3: 勤務 終了時刻 | E3: 勤務時間 (h) | F3: 給与 (円) | G3: 勤務 エリア | H3: 通勤 手段 | I3: 往復 交通費(円) | J3: 仕入れ 店舗 | K3: 仕入れ 合計金額(円) | L3: 支払 方法 | M3: 送料 (円) | N3: その他経費 （内容） | O3: その他経費 （金額円）
A4: 1/1 | B4: 木 | E4: =IF(AND(C4<>"",D4<>""),IF(D4>=C4,ROUND((D4-C4)*24,2),ROUND((D4-C4+1)*24,2)),"") | F4: =IF(E4<>"",ROUND(E4*$I$2,0),"")
A5: 1/2 | B5: 金 | E5: =IF(AND(C5<>"",D5<>""),IF(D5>=C5,ROUND((D5-C5)*24,2),ROUND((D5-C5+1)*24,2)),"") | F5: =IF(E5<>"",ROUND(E5*$I$2,0),"")
A6: 1/3 | B6: 土 | E6: =IF(AND(C6<>"",D6<>""),IF(D6>=C6,ROUND((D6-C6)*24,2),ROUND((D6-C6+1)*24,2)),"") | F6: =IF(E6<>"",ROUND(E6*$I$2,0),"")
A7: 1/4 | B7: 日 | E7: =IF(AND(C7<>"",D7<>""),IF(D7>=C7,ROUND((D7-C7)*24,2),ROUND((D7-C7+1)*24,2)),"") | F7: =IF(E7<>"",ROUND(E7*$I$2,0),"")
A8: 1/5 | B8: 月 | E8: =IF(AND(C8<>"",D8<>""),IF(D8>=C8,ROUND((D8-C8)*24,2),ROUND((D8-C8+1)*24,2)),"") | F8: =IF(E8<>"",ROUND(E8*$I$2,0),"")
A9: 1/6 | B9: 火 | E9: =IF(AND(C9<>"",D9<>""),IF(D9>=C9,ROUND((D9-C9)*24,2),ROUND((D9-C9+1)*24,2)),"") | F9: =IF(E9<>"",ROUND(E9*$I$2,0),"")
A10: 1/7 | B10: 水 | E10: =IF(AND(C10<>"",D10<>""),IF(D10>=C10,ROUND((D10-C10)*24,2),ROUND((D10-C10+1)*24,2)),"") | F10: =IF(E10<>"",ROUND(E10*$I$2,0),"")
A11: 1/8 | B11: 木 | E11: =IF(AND(C11<>"",D11<>""),IF(D11>=C11,ROUND((D11-C11)*24,2),ROUND((D11-C11+1)*24,2)),"") | F11: =IF(E11<>"",ROUND(E11*$I$2,0),"")
A12: 1/9 | B12: 金 | E12: =IF(AND(C12<>"",D12<>""),IF(D12>=C12,ROUND((D12-C12)*24,2),ROUND((D12-C12+1)*24,2)),"") | F12: =IF(E12<>"",ROUND(E12*$I$2,0),"")
A13: 1/10 | B13: 土 | E13: =IF(AND(C13<>"",D13<>""),IF(D13>=C13,ROUND((D13-C13)*24,2),ROUND((D13-C13+1)*24,2)),"") | F13: =IF(E13<>"",ROUND(E13*$I$2,0),"")
A14: 1/11 | B14: 日 | E14: =IF(AND(C14<>"",D14<>""),IF(D14>=C14,ROUND((D14-C14)*24,2),ROUND((D14-C14+1)*24,2)),"") | F14: =IF(E14<>"",ROUND(E14*$I$2,0),"")
A15: 1/12 | B15: 月 | E15: =IF(AND(C15<>"",D15<>""),IF(D15>=C15,ROUND((D15-C15)*24,2),ROUND((D15-C15+1)*24,2)),"") | F15: =IF(E15<>"",ROUND(E15*$I$2,0),"")
... A34: 1/31 | B34: 土 | E34: =IF(AND(C34<>"",D34<>""),IF(D34>=C34,ROUND((D34-C34)*24,2),ROUND((D34-C34+1)*24,2)),"") | F34: =IF(E34<>"",ROUND(E34*$I$2,0),"")
A36: ■ 月次集計サマリー
A37: 勤務日数 | F37: =COUNT(E4:E34) -> 0
A38: 総勤務時間 | F38: =SUM(E4:E34) -> 0
A39: 給与合計 | F39: =SUM(F4:F34) -> 0
A40: 源泉所得税（乙欄） | F40: =IF(F39=0,0,IFERROR(VLOOKUP(F39,税額表!$A$2:$B$74,2,TRUE()),0)) -> 0
A41: 差引給与（税引後） | F41: =F39-F40 -> 0
A42: 交通費合計 | F42: =SUM(I4:I34) -> 0
A43: 立替金（現金＋個人カード） | F43: =SUMIF(L4:L34,"現金",K4:K34)+SUMIF(L4:L34,"個人カード",K4:K34) -> 0
A44: 送料合計 | F44: =SUM(M4:M34) -> 0
A45: その他経費合計 | F45: =SUM(O4:O34) -> 0
A46: 前月繰越立替金 | F46: 0
A47: 総支給額（振込予定額） | F47: =F41+F42+F43+F44+F45+F46 -> 0
A49: 【入力セル凡例】 | C49: 平日入力 | E49: 土曜 | G49: 日曜 | I49: 送料・その他経費 | K49: 前月繰越（手入力）
A50: 【注記】① 開始・終了時刻は「9:00」形式で入力 ② 源泉所得税は令和6年分月額表乙欄概算（詳細は国税庁HP参照） ③ 立替金＝現金・個人カード支払いの仕入れ金額合計 ④ 送料・その他経費も総支給額に含まれます ⑤ 前月繰越立替金は前月の立替金を自動参照（1月のみ黄色セルに手入力）

Sheet 2月
A1: 2026年 2月 アルバイト勤怠表
A2: 従業員名 | C2: 仲本 正 | G2: 時 給 | I2: 1300 | L2: （税区分：乙欄 雇用保険なし）
A3: 日 付 | B3: 曜 日 | C3: 勤務 開始時刻 | D3: 勤務 終了時刻 | E3: 勤務時間 (h) | F3: 給与 (円) | G3: 勤務 エリア | H3: 通勤 手段 | I3: 往復 交通費(円) | J3: 仕入れ 店舗 | K3: 仕入れ 合計金額(円) | L3: 支払 方法 | M3: 送料 (円) | N3: その他経費 （内容） | O3: その他経費 （金額円）
A4: 2/1 | B4: 日 | E4: =IF(AND(C4<>"",D4<>""),IF(D4>=C4,ROUND((D4-C4)*24,2),ROUND((D4-C4+1)*24,2)),"") | F4: =IF(E4<>"",ROUND(E4*$I$2,0),"")
A5: 2/2 | B5: 月 | E5: =IF(AND(C5<>"",D5<>""),IF(D5>=C5,ROUND((D5-C5)*24,2),ROUND((D5-C5+1)*24,2)),"") | F5: =IF(E5<>"",ROUND(E5*$I$2,0),"")
A6: 2/3 | B6: 火 | E6: =IF(AND(C6<>"",D6<>""),IF(D6>=C6,ROUND((D6-C6)*24,2),ROUND((D6-C6+1)*24,2)),"") | F6: =IF(E6<>"",ROUND(E6*$I$2,0),"")
A7: 2/4 | B7: 水 | E7: =IF(AND(C7<>"",D7<>""),IF(D7>=C7,ROUND((D7-C7)*24,2),ROUND((D7-C7+1)*24,2)),"") | F7: =IF(E7<>"",ROUND(E7*$I$2,0),"")
A8: 2/5 | B8: 木 | E8: =IF(AND(C8<>"",D8<>""),IF(D8>=C8,ROUND((D8-C8)*24,2),ROUND((D8-C8+1)*24,2)),"") | F8: =IF(E8<>"",ROUND(E8*$I$2,0),"")
A9: 2/6 | B9: 金 | E9: =IF(AND(C9<>"",D9<>""),IF(D9>=C9,ROUND((D9-C9)*24,2),ROUND((D9-C9+1)*24,2)),"") | F9: =IF(E9<>"",ROUND(E9*$I$2,0),"")
A10: 2/7 | B10: 土 | E10: =IF(AND(C10<>"",D10<>""),IF(D10>=C10,ROUND((D10-C10)*24,2),ROUND((D10-C10+1)*24,2)),"") | F10: =IF(E10<>"",ROUND(E10*$I$2,0),"")
A11: 2/8 | B11: 日 | E11: =IF(AND(C11<>"",D11<>""),IF(D11>=C11,ROUND((D11-C11)*24,2),ROUND((D11-C11+1)*24,2)),"") | F11: =IF(E11<>"",ROUND(E11*$I$2,0),"")
A12: 2/9 | B12: 月 | E12: =IF(AND(C12<>"",D12<>""),IF(D12>=C12,ROUND((D12-C12)*24,2),ROUND((D12-C12+1)*24,2)),"") | F12: =IF(E12<>"",ROUND(E12*$I$2,0),"")
A13: 2/10 | B13: 火 | E13: =IF(AND(C13<>"",D13<>""),IF(D13>=C13,ROUND((D13-C13)*24,2),ROUND((D13-C13+1)*24,2)),"") | F13: =IF(E13<>"",ROUND(E13*$I$2,0),"")
A14: 2/11 | B14: 水 | E14: =IF(AND(C14<>"",D14<>""),IF(D14>=C14,ROUND((D14-C14)*24,2),ROUND((D14-C14+1)*24,2)),"") | F14: =IF(E14<>"",ROUND(E14*$I$2,0),"")
A15: 2/12 | B15: 木 | E15: =IF(AND(C15<>"",D15<>""),IF(D15>=C15,ROUND((D15-C15)*24,2),ROUND((D15-C15+1)*24,2)),"") | F15: =IF(E15<>"",ROUND(E15*$I$2,0),"")
... A31: 2/28 | B31: 土 | E31: =IF(AND(C31<>"",D31<>""),IF(D31>=C31,ROUND((D31-C31)*24,2),ROUND((D31-C31+1)*24,2)),"") | F31: =IF(E31<>"",ROUND(E31*$I$2,0),"")
A33: ■ 月次集計サマリー
A34: 勤務日数 | F34: =COUNT(E4:E31) -> 0
A35: 総勤務時間 | F35: =SUM(E4:E31) -> 0
A36: 給与合計 | F36: =SUM(F4:F31) -> 0
A37: 源泉所得税（乙欄） | F37: =IF(F36=0,0,IFERROR(VLOOKUP(F36,税額表!$A$2:$B$74,2,TRUE()),0)) -> 0
A38: 差引給与（税引後） | F38: =F36-F37 -> 0
A39: 交通費合計 | F39: =SUM(I4:I31) -> 0
A40: 立替金（現金＋個人カード） | F40: =SUMIF(L4:L31,"現金",K4:K31)+SUMIF(L4:L31,"個人カード",K4:K31) -> 0
A41: 送料合計 | F41: =SUM(M4:M31) -> 0
A42: その他経費合計 | F42: =SUM(O4:O31) -> 0
A43: 前月繰越立替金 | F43: ='1月'!F43 -> 0
A44: 総支給額（振込予定額） | F44: =F38+F39+F40+F41+F42+F43 -> 0
A46: 【入力セル凡例】 | C46: 平日入力 | E46: 土曜 | G46: 日曜 | I46: 送料・その他経費 | K46: 前月繰越（自動）
A47: 【注記】① 開始・終了時刻は「9:00」形式で入力 ② 源泉所得税は令和6年分月額表乙欄概算（詳細は国税庁HP参照） ③ 立替金＝現金・個人カード支払いの仕入れ金額合計 ④ 送料・その他経費も総支給額に含まれます ⑤ 前月繰越立替金は前月の立替金を自動参照（1月のみ黄色セルに手入力）

Sheet 3月
A1: 2026年 3月 アルバイト勤怠表
A2: 従業員名 | C2: 仲本 正 | G2: 時 給 | I2: 1300 | L2: （税区分：乙欄 雇用保険なし）
A3: 日 付 | B3: 曜 日 | C3: 勤務 開始時刻 | D3: 勤務 終了時刻 | E3: 勤務時間 (h) | F3: 給与 (円) | G3: 勤務 エリア | H3: 通勤 手段 | I3: 往復 交通費(円) | J3: 仕入れ 店舗 | K3: 仕入れ 合計金額(円) | L3: 支払 方法 | M3: 送料 (円) | N3: その他経費 （内容） | O3: その他経費 （金額円）
A4: 3/1 | B4: 日 | E4: =IF(AND(C4<>"",D4<>""),IF(D4>=C4,ROUND((D4-C4)*24,2),ROUND((D4-C4+1)*24,2)),"") | F4: =IF(E4<>"",ROUND(E4*$I$2,0),"")
A5: 3/2 | B5: 月 | E5: =IF(AND(C5<>"",D5<>""),IF(D5>=C5,ROUND((D5-C5)*24,2),ROUND((D5-C5+1)*24,2)),"") | F5: =IF(E5<>"",ROUND(E5*$I$2,0),"")
A6: 3/3 | B6: 火 | E6: =IF(AND(C6<>"",D6<>""),IF(D6>=C6,ROUND((D6-C6)*24,2),ROUND((D6-C6+1)*24,2)),"") | F6: =IF(E6<>"",ROUND(E6*$I$2,0),"")
A7: 3/4 | B7: 水 | E7: =IF(AND(C7<>"",D7<>""),IF(D7>=C7,ROUND((D7-C7)*24,2),ROUND((D7-C7+1)*24,2)),"") | F7: =IF(E7<>"",ROUND(E7*$I$2,0),"")
A8: 3/5 | B8: 木 | E8: =IF(AND(C8<>"",D8<>""),IF(D8>=C8,ROUND((D8-C8)*24,2),ROUND((D8-C8+1)*24,2)),"") | F8: =IF(E8<>"",ROUND(E8*$I$2,0),"")
A9: 3/6 | B9: 金 | E9: =IF(AND(C9<>"",D9<>""),IF(D9>=C9,ROUND((D9-C9)*24,2),ROUND((D9-C9+1)*24,2)),"") | F9: =IF(E9<>"",ROUND(E9*$I$2,0),"")
A10: 3/7 | B10: 土 | E10: =IF(AND(C10<>"",D10<>""),IF(D10>=C10,ROUND((D10-C10)*24,2),ROUND((D10-C10+1)*24,2)),"") | F10: =IF(E10<>"",ROUND(E10*$I$2,0),"")
A11: 3/8 | B11: 日 | E11: =IF(AND(C11<>"",D11<>""),IF(D11>=C11,ROUND((D11-C11)*24,2),ROUND((D11-C11+1)*24,2)),"") | F11: =IF(E11<>"",ROUND(E11*$I$2,0),"")
A12: 3/9 | B12: 月 | E12: =IF(AND(C12<>"",D12<>""),IF(D12>=C12,ROUND((D12-C12)*24,2),ROUND((D12-C12+1)*24,2)),"") | F12: =IF(E12<>"",ROUND(E12*$I$2,0),"")
A13: 3/10 | B13: 火 | E13: =IF(AND(C13<>"",D13<>""),IF(D13>=C13,ROUND((D13-C13)*24,2),ROUND((D13-C13+1)*24,2)),"") | F13: =IF(E13<>"",ROUND(E13*$I$2,0),"")
A14: 3/11 | B14: 水 | E14: =IF(AND(C14<>"",D14<>""),IF(D14>=C14,ROUND((D14-C14)*24,2),ROUND((D14-C14+1)*24,2)),"") | F14: =IF(E14<>"",ROUND(E14*$I$2,0),"")
A15: 3/12 | B15: 木 | E15: =IF(AND(C15<>"",D15<>""),IF(D15>=C15,ROUND((D15-C15)*24,2),ROUND((D15-C15+1)*24,2)),"") | F15: =IF(E15<>"",ROUND(E15*$I$2,0),"")
... A34: 3/31 | B34: 火 | E34: =IF(AND(C34<>"",D34<>""),IF(D34>=C34,ROUND((D34-C34)*24,2),ROUND((D34-C34+1)*24,2)),"") | F34: =IF(E34<>"",ROUND(E34*$I$2,0),"")
A36: ■ 月次集計サマリー
A37: 勤務日数 | F37: =COUNT(E4:E34) -> 0
A38: 総勤務時間 | F38: =SUM(E4:E34) -> 0
A39: 給与合計 | F39: =SUM(F4:F34) -> 0
A40: 源泉所得税（乙欄） | F40: =IF(F39=0,0,IFERROR(VLOOKUP(F39,税額表!$A$2:$B$74,2,TRUE()),0)) -> 0
A41: 差引給与（税引後） | F41: =F39-F40 -> 0
A42: 交通費合計 | F42: =SUM(I4:I34) -> 0
A43: 立替金（現金＋個人カード） | F43: =SUMIF(L4:L34,"現金",K4:K34)+SUMIF(L4:L34,"個人カード",K4:K34) -> 0
A44: 送料合計 | F44: =SUM(M4:M34) -> 0
A45: その他経費合計 | F45: =SUM(O4:O34) -> 0
A46: 前月繰越立替金 | F46: ='2月'!F40 -> 0
A47: 総支給額（振込予定額） | F47: =F41+F42+F43+F44+F45+F46 -> 0
A49: 【入力セル凡例】 | C49: 平日入力 | E49: 土曜 | G49: 日曜 | I49: 送料・その他経費 | K49: 前月繰越（自動）
A50: 【注記】① 開始・終了時刻は「9:00」形式で入力 ② 源泉所得税は令和6年分月額表乙欄概算（詳細は国税庁HP参照） ③ 立替金＝現金・個人カード支払いの仕入れ金額合計 ④ 送料・その他経費も総支給額に含まれます ⑤ 前月繰越立替金は前月の立替金を自動参照（1月のみ黄色セルに手入力）

Sheet 4月
A1: 2026年 4月 アルバイト勤怠表
A2: 従業員名 | C2: 仲本 正 | G2: 時 給 | I2: 1300 | L2: （税区分：乙欄 雇用保険なし）
A3: 日 付 | B3: 曜 日 | C3: 勤務 開始時刻 | D3: 勤務 終了時刻 | E3: 勤務時間 (h) | F3: 給与 (円) | G3: 勤務 エリア | H3: 通勤 手段 | I3: 往復 交通費(円) | J3: 仕入れ 店舗 | K3: 仕入れ 合計金額(円) | L3: 支払 方法 | M3: 送料 (円) | N3: その他経費 （内容） | O3: その他経費 （金額円）
A4: 4/1 | B4: 水 | E4: =IF(AND(C4<>"",D4<>""),IF(D4>=C4,ROUND((D4-C4)*24,2),ROUND((D4-C4+1)*24,2)),"") | F4: =IF(E4<>"",ROUND(E4*$I$2,0),"")
A5: 4/2 | B5: 木 | E5: =IF(AND(C5<>"",D5<>""),IF(D5>=C5,ROUND((D5-C5)*24,2),ROUND((D5-C5+1)*24,2)),"") | F5: =IF(E5<>"",ROUND(E5*$I$2,0),"")
A6: 4/3 | B6: 金 | E6: =IF(AND(C6<>"",D6<>""),IF(D6>=C6,ROUND((D6-C6)*24,2),ROUND((D6-C6+1)*24,2)),"") | F6: =IF(E6<>"",ROUND(E6*$I$2,0),"")
A7: 4/4 | B7: 土 | E7: =IF(AND(C7<>"",D7<>""),IF(D7>=C7,ROUND((D7-C7)*24,2),ROUND((D7-C7+1)*24,2)),"") | F7: =IF(E7<>"",ROUND(E7*$I$2,0),"")
A8: 4/5 | B8: 日 | E8: =IF(AND(C8<>"",D8<>""),IF(D8>=C8,ROUND((D8-C8)*24,2),ROUND((D8-C8+1)*24,2)),"") | F8: =IF(E8<>"",ROUND(E8*$I$2,0),"")
A9: 4/6 | B9: 月 | E9: =IF(AND(C9<>"",D9<>""),IF(D9>=C9,ROUND((D9-C9)*24,2),ROUND((D9-C9+1)*24,2)),"") | F9: =IF(E9<>"",ROUND(E9*$I$2,0),"")
A10: 4/7 | B10: 火 | E10: =IF(AND(C10<>"",D10<>""),IF(D10>=C10,ROUND((D10-C10)*24,2),ROUND((D10-C10+1)*24,2)),"") | F10: =IF(E10<>"",ROUND(E10*$I$2,0),"")
A11: 4/8 | B11: 水 | E11: =IF(AND(C11<>"",D11<>""),IF(D11>=C11,ROUND((D11-C11)*24,2),ROUND((D11-C11+1)*24,2)),"") | F11: =IF(E11<>"",ROUND(E11*$I$2,0),"")
A12: 4/9 | B12: 木 | E12: =IF(AND(C12<>"",D12<>""),IF(D12>=C12,ROUND((D12-C12)*24,2),ROUND((D12-C12+1)*24,2)),"") | F12: =IF(E12<>"",ROUND(E12*$I$2,0),"")
A13: 4/10 | B13: 金 | E13: =IF(AND(C13<>"",D13<>""),IF(D13>=C13,ROUND((D13-C13)*24,2),ROUND((D13-C13+1)*24,2)),"") | F13: =IF(E13<>"",ROUND(E13*$I$2,0),"")
A14: 4/11 | B14: 土 | E14: =IF(AND(C14<>"",D14<>""),IF(D14>=C14,ROUND((D14-C14)*24,2),ROUND((D14-C14+1)*24,2)),"") | F14: =IF(E14<>"",ROUND(E14*$I$2,0),"")
A15: 4/12 | B15: 日 | E15: =IF(AND(C15<>"",D15<>""),IF(D15>=C15,ROUND((D15-C15)*24,2),ROUND((D15-C15+1)*24,2)),"") | F15: =IF(E15<>"",ROUND(E15*$I$2,0),"")
... A33: 4/30 | B33: 木 | E33: =IF(AND(C33<>"",D33<>""),IF(D33>=C33,ROUND((D33-C33)*24,2),ROUND((D33-C33+1)*24,2)),"") | F33: =IF(E33<>"",ROUND(E33*$I$2,0),"")
A35: ■ 月次集計サマリー
A36: 勤務日数 | F36: =COUNT(E4:E33) -> 0
A37: 総勤務時間 | F37: =SUM(E4:E33) -> 0
A38: 給与合計 | F38: =SUM(F4:F33) -> 0
A39: 源泉所得税（乙欄） | F39: =IF(F38=0,0,IFERROR(VLOOKUP(F38,税額表!$A$2:$B$74,2,TRUE()),0)) -> 0
A40: 差引給与（税引後） | F40: =F38-F39 -> 0
A41: 交通費合計 | F41: =SUM(I4:I33) -> 0
A42: 立替金（現金＋個人カード） | F42: =SUMIF(L4:L33,"現金",K4:K33)+SUMIF(L4:L33,"個人カード",K4:K33) -> 0
A43: 送料合計 | F43: =SUM(M4:M33) -> 0
A44: その他経費合計 | F44: =SUM(O4:O33) -> 0
A45: 前月繰越立替金 | F45: ='3月'!F43 -> 0
A46: 総支給額（振込予定額） | F46: =F40+F41+F42+F43+F44+F45 -> 0
A48: 【入力セル凡例】 | C48: 平日入力 | E48: 土曜 | G48: 日曜 | I48: 送料・その他経費 | K48: 前月繰越（自動）
A49: 【注記】① 開始・終了時刻は「9:00」形式で入力 ② 源泉所得税は令和6年分月額表乙欄概算（詳細は国税庁HP参照） ③ 立替金＝現金・個人カード支払いの仕入れ金額合計 ④ 送料・その他経費も総支給額に含まれます ⑤ 前月繰越立替金は前月の立替金を自動参照（1月のみ黄色セルに手入力）

Sheet 5月
A1: 2026年 5月 アルバイト勤怠表
A2: 従業員名 | C2: 仲本 正 | G2: 時 給 | I2: 1300 | L2: （税区分：乙欄 雇用保険なし）
A3: 日 付 | B3: 曜 日 | C3: 勤務 開始時刻 | D3: 勤務 終了時刻 | E3: 勤務時間 (h) | F3: 給与 (円) | G3: 勤務 エリア | H3: 通勤 手段 | I3: 往復 交通費(円) | J3: 仕入れ 店舗 | K3: 仕入れ 合計金額(円) | L3: 支払 方法 | M3: 送料 (円) | N3: その他経費 （内容） | O3: その他経費 （金額円）
A4: 5/1 | B4: 金 | E4: =IF(AND(C4<>"",D4<>""),IF(D4>=C4,ROUND((D4-C4)*24,2),ROUND((D4-C4+1)*24,2)),"") | F4: =IF(E4<>"",ROUND(E4*$I$2,0),"")
A5: 5/2 | B5: 土 | E5: =IF(AND(C5<>"",D5<>""),IF(D5>=C5,ROUND((D5-C5)*24,2),ROUND((D5-C5+1)*24,2)),"") | F5: =IF(E5<>"",ROUND(E5*$I$2,0),"")
A6: 5/3 | B6: 日 | E6: =IF(AND(C6<>"",D6<>""),IF(D6>=C6,ROUND((D6-C6)*24,2),ROUND((D6-C6+1)*24,2)),"") | F6: =IF(E6<>"",ROUND(E6*$I$2,0),"")
A7: 5/4 | B7: 月 | E7: =IF(AND(C7<>"",D7<>""),IF(D7>=C7,ROUND((D7-C7)*24,2),ROUND((D7-C7+1)*24,2)),"") | F7: =IF(E7<>"",ROUND(E7*$I$2,0),"")
A8: 5/5 | B8: 火 | E8: =IF(AND(C8<>"",D8<>""),IF(D8>=C8,ROUND((D8-C8)*24,2),ROUND((D8-C8+1)*24,2)),"") | F8: =IF(E8<>"",ROUND(E8*$I$2,0),"")
A9: 5/6 | B9: 水 | E9: =IF(AND(C9<>"",D9<>""),IF(D9>=C9,ROUND((D9-C9)*24,2),ROUND((D9-C9+1)*24,2)),"") | F9: =IF(E9<>"",ROUND(E9*$I$2,0),"")
A10: 5/7 | B10: 木 | E10: =IF(AND(C10<>"",D10<>""),IF(D10>=C10,ROUND((D10-C10)*24,2),ROUND((D10-C10+1)*24,2)),"") | F10: =IF(E10<>"",ROUND(E10*$I$2,0),"")
A11: 5/8 | B11: 金 | E11: =IF(AND(C11<>"",D11<>""),IF(D11>=C11,ROUND((D11-C11)*24,2),ROUND((D11-C11+1)*24,2)),"") | F11: =IF(E11<>"",ROUND(E11*$I$2,0),"")
A12: 5/9 | B12: 土 | E12: =IF(AND(C12<>"",D12<>""),IF(D12>=C12,ROUND((D12-C12)*24,2),ROUND((D12-C12+1)*24,2)),"") | F12: =IF(E12<>"",ROUND(E12*$I$2,0),"")
A13: 5/10 | B13: 日 | E13: =IF(AND(C13<>"",D13<>""),IF(D13>=C13,ROUND((D13-C13)*24,2),ROUND((D13-C13+1)*24,2)),"") | F13: =IF(E13<>"",ROUND(E13*$I$2,0),"")
A14: 5/11 | B14: 月 | E14: =IF(AND(C14<>"",D14<>""),IF(D14>=C14,ROUND((D14-C14)*24,2),ROUND((D14-C14+1)*24,2)),"") | F14: =IF(E14<>"",ROUND(E14*$I$2,0),"")
A15: 5/12 | B15: 火 | E15: =IF(AND(C15<>"",D15<>""),IF(D15>=C15,ROUND((D15-C15)*24,2),ROUND((D15-C15+1)*24,2)),"") | F15: =IF(E15<>"",ROUND(E15*$I$2,0),"")
... A34: 5/31 | B34: 日 | E34: =IF(AND(C34<>"",D34<>""),IF(D34>=C34,ROUND((D34-C34)*24,2),ROUND((D34-C34+1)*24,2)),"") | F34: =IF(E34<>"",ROUND(E34*$I$2,0),"")
A36: ■ 月次集計サマリー
A37: 勤務日数 | F37: =COUNT(E4:E34) -> 0
A38: 総勤務時間 | F38: =SUM(E4:E34) -> 0
A39: 給与合計 | F39: =SUM(F4:F34) -> 0
A40: 源泉所得税（乙欄） | F40: =IF(F39=0,0,IFERROR(VLOOKUP(F39,税額表!$A$2:$B$74,2,TRUE()),0)) -> 0
A41: 差引給与（税引後） | F41: =F39-F40 -> 0
A42: 交通費合計 | F42: =SUM(I4:I34) -> 0
A43: 立替金（現金＋個人カード） | F43: =SUMIF(L4:L34,"現金",K4:K34)+SUMIF(L4:L34,"個人カード",K4:K34) -> 0
A44: 送料合計 | F44: =SUM(M4:M34) -> 0
A45: その他経費合計 | F45: =SUM(O4:O34) -> 0
A46: 前月繰越立替金 | F46: ='4月'!F42 -> 0
A47: 総支給額（振込予定額） | F47: =F41+F42+F43+F44+F45+F46 -> 0
A49: 【入力セル凡例】 | C49: 平日入力 | E49: 土曜 | G49: 日曜 | I49: 送料・その他経費 | K49: 前月繰越（自動）
A50: 【注記】① 開始・終了時刻は「9:00」形式で入力 ② 源泉所得税は令和6年分月額表乙欄概算（詳細は国税庁HP参照） ③ 立替金＝現金・個人カード支払いの仕入れ金額合計 ④ 送料・その他経費も総支給額に含まれます ⑤ 前月繰越立替金は前月の立替金を自動参照（1月のみ黄色セルに手入力）

Sheet 6月
A1: 2026年 6月 アルバイト勤怠表
A2: 従業員名 | C2: 仲本 正 | G2: 時 給 | I2: 1300 | L2: （税区分：乙欄 雇用保険なし）
A3: 日 付 | B3: 曜 日 | C3: 勤務 開始時刻 | D3: 勤務 終了時刻 | E3: 勤務時間 (h) | F3: 給与 (円) | G3: 勤務 エリア | H3: 通勤 手段 | I3: 往復 交通費(円) | J3: 仕入れ 店舗 | K3: 仕入れ 合計金額(円) | L3: 支払 方法 | M3: 送料 (円) | N3: その他経費 （内容） | O3: その他経費 （金額円）
A4: 6/1 | B4: 月 | E4: =IF(AND(C4<>"",D4<>""),IF(D4>=C4,ROUND((D4-C4)*24,2),ROUND((D4-C4+1)*24,2)),"") | F4: =IF(E4<>"",ROUND(E4*$I$2,0),"")
A5: 6/2 | B5: 火 | E5: =IF(AND(C5<>"",D5<>""),IF(D5>=C5,ROUND((D5-C5)*24,2),ROUND((D5-C5+1)*24,2)),"") | F5: =IF(E5<>"",ROUND(E5*$I$2,0),"")
A6: 6/3 | B6: 水 | E6: =IF(AND(C6<>"",D6<>""),IF(D6>=C6,ROUND((D6-C6)*24,2),ROUND((D6-C6+1)*24,2)),"") | F6: =IF(E6<>"",ROUND(E6*$I$2,0),"")
A7: 6/4 | B7: 木 | E7: =IF(AND(C7<>"",D7<>""),IF(D7>=C7,ROUND((D7-C7)*24,2),ROUND((D7-C7+1)*24,2)),"") | F7: =IF(E7<>"",ROUND(E7*$I$2,0),"")
A8: 6/5 | B8: 金 | E8: =IF(AND(C8<>"",D8<>""),IF(D8>=C8,ROUND((D8-C8)*24,2),ROUND((D8-C8+1)*24,2)),"") | F8: =IF(E8<>"",ROUND(E8*$I$2,0),"")
A9: 6/6 | B9: 土 | E9: =IF(AND(C9<>"",D9<>""),IF(D9>=C9,ROUND((D9-C9)*24,2),ROUND((D9-C9+1)*24,2)),"") | F9: =IF(E9<>"",ROUND(E9*$I$2,0),"")
A10: 6/7 | B10: 日 | E10: =IF(AND(C10<>"",D10<>""),IF(D10>=C10,ROUND((D10-C10)*24,2),ROUND((D10-C10+1)*24,2)),"") | F10: =IF(E10<>"",ROUND(E10*$I$2,0),"")
A11: 6/8 | B11: 月 | E11: =IF(AND(C11<>"",D11<>""),IF(D11>=C11,ROUND((D11-C11)*24,2),ROUND((D11-C11+1)*24,2)),"") | F11: =IF(E11<>"",ROUND(E11*$I$2,0),"")
A12: 6/9 | B12: 火 | E12: =IF(AND(C12<>"",D12<>""),IF(D12>=C12,ROUND((D12-C12)*24,2),ROUND((D12-C12+1)*24,2)),"") | F12: =IF(E12<>"",ROUND(E12*$I$2,0),"")
A13: 6/10 | B13: 水 | E13: =IF(AND(C13<>"",D13<>""),IF(D13>=C13,ROUND((D13-C13)*24,2),ROUND((D13-C13+1)*24,2)),"") | F13: =IF(E13<>"",ROUND(E13*$I$2,0),"")
A14: 6/11 | B14: 木 | E14: =IF(AND(C14<>"",D14<>""),IF(D14>=C14,ROUND((D14-C14)*24,2),ROUND((D14-C14+1)*24,2)),"") | F14: =IF(E14<>"",ROUND(E14*$I$2,0),"")
A15: 6/12 | B15: 金 | E15: =IF(AND(C15<>"",D15<>""),IF(D15>=C15,ROUND((D15-C15)*24,2),ROUND((D15-C15+1)*24,2)),"") | F15: =IF(E15<>"",ROUND(E15*$I$2,0),"")
... A33: 6/30 | B33: 火 | E33: =IF(AND(C33<>"",D33<>""),IF(D33>=C33,ROUND((D33-C33)*24,2),ROUND((D33-C33+1)*24,2)),"") | F33: =IF(E33<>"",ROUND(E33*$I$2,0),"")
A35: ■ 月次集計サマリー
A36: 勤務日数 | F36: =COUNT(E4:E33) -> 0
A37: 総勤務時間 | F37: =SUM(E4:E33) -> 0
A38: 給与合計 | F38: =SUM(F4:F33) -> 0
A39: 源泉所得税（乙欄） | F39: =IF(F38=0,0,IFERROR(VLOOKUP(F38,税額表!$A$2:$B$74,2,TRUE()),0)) -> 0
A40: 差引給与（税引後） | F40: =F38-F39 -> 0
A41: 交通費合計 | F41: =SUM(I4:I33) -> 0
A42: 立替金（現金＋個人カード） | F42: =SUMIF(L4:L33,"現金",K4:K33)+SUMIF(L4:L33,"個人カード",K4:K33) -> 0
A43: 送料合計 | F43: =SUM(M4:M33) -> 0
A44: その他経費合計 | F44: =SUM(O4:O33) -> 0
A45: 前月繰越立替金 | F45: ='5月'!F43 -> 0
A46: 総支給額（振込予定額） | F46: =F40+F41+F42+F43+F44+F45 -> 0
A48: 【入力セル凡例】 | C48: 平日入力 | E48: 土曜 | G48: 日曜 | I48: 送料・その他経費 | K48: 前月繰越（自動）
A49: 【注記】① 開始・終了時刻は「9:00」形式で入力 ② 源泉所得税は令和6年分月額表乙欄概算（詳細は国税庁HP参照） ③ 立替金＝現金・個人カード支払いの仕入れ金額合計 ④ 送料・その他経費も総支給額に含まれます ⑤ 前月繰越立替金は前月の立替金を自動参照（1月のみ黄色セルに手入力）

Sheet 7月
A1: 2026年 7月 アルバイト勤怠表
A2: 従業員名 | C2: 仲本 正 | G2: 時 給 | I2: 1300 | L2: （税区分：乙欄 雇用保険なし）
A3: 日 付 | B3: 曜 日 | C3: 勤務 開始時刻 | D3: 勤務 終了時刻 | E3: 勤務時間 (h) | F3: 給与 (円) | G3: 勤務 エリア | H3: 通勤 手段 | I3: 往復 交通費(円) | J3: 仕入れ 店舗 | K3: 仕入れ 合計金額(円) | L3: 支払 方法 | M3: 送料 (円) | N3: その他経費 （内容） | O3: その他経費 （金額円）
A4: 7/1 | B4: 水 | E4: =IF(AND(C4<>"",D4<>""),IF(D4>=C4,ROUND((D4-C4)*24,2),ROUND((D4-C4+1)*24,2)),"") | F4: =IF(E4<>"",ROUND(E4*$I$2,0),"")
A5: 7/2 | B5: 木 | E5: =IF(AND(C5<>"",D5<>""),IF(D5>=C5,ROUND((D5-C5)*24,2),ROUND((D5-C5+1)*24,2)),"") | F5: =IF(E5<>"",ROUND(E5*$I$2,0),"")
A6: 7/3 | B6: 金 | E6: =IF(AND(C6<>"",D6<>""),IF(D6>=C6,ROUND((D6-C6)*24,2),ROUND((D6-C6+1)*24,2)),"") | F6: =IF(E6<>"",ROUND(E6*$I$2,0),"")
A7: 7/4 | B7: 土 | E7: =IF(AND(C7<>"",D7<>""),IF(D7>=C7,ROUND((D7-C7)*24,2),ROUND((D7-C7+1)*24,2)),"") | F7: =IF(E7<>"",ROUND(E7*$I$2,0),"")
A8: 7/5 | B8: 日 | E8: =IF(AND(C8<>"",D8<>""),IF(D8>=C8,ROUND((D8-C8)*24,2),ROUND((D8-C8+1)*24,2)),"") | F8: =IF(E8<>"",ROUND(E8*$I$2,0),"")
A9: 7/6 | B9: 月 | E9: =IF(AND(C9<>"",D9<>""),IF(D9>=C9,ROUND((D9-C9)*24,2),ROUND((D9-C9+1)*24,2)),"") | F9: =IF(E9<>"",ROUND(E9*$I$2,0),"")
A10: 7/7 | B10: 火 | E10: =IF(AND(C10<>"",D10<>""),IF(D10>=C10,ROUND((D10-C10)*24,2),ROUND((D10-C10+1)*24,2)),"") | F10: =IF(E10<>"",ROUND(E10*$I$2,0),"")
A11: 7/8 | B11: 水 | E11: =IF(AND(C11<>"",D11<>""),IF(D11>=C11,ROUND((D11-C11)*24,2),ROUND((D11-C11+1)*24,2)),"") | F11: =IF(E11<>"",ROUND(E11*$I$2,0),"")
A12: 7/9 | B12: 木 | E12: =IF(AND(C12<>"",D12<>""),IF(D12>=C12,ROUND((D12-C12)*24,2),ROUND((D12-C12+1)*24,2)),"") | F12: =IF(E12<>"",ROUND(E12*$I$2,0),"")
A13: 7/10 | B13: 金 | E13: =IF(AND(C13<>"",D13<>""),IF(D13>=C13,ROUND((D13-C13)*24,2),ROUND((D13-C13+1)*24,2)),"") | F13: =IF(E13<>"",ROUND(E13*$I$2,0),"")
A14: 7/11 | B14: 土 | E14: =IF(AND(C14<>"",D14<>""),IF(D14>=C14,ROUND((D14-C14)*24,2),ROUND((D14-C14+1)*24,2)),"") | F14: =IF(E14<>"",ROUND(E14*$I$2,0),"")
A15: 7/12 | B15: 日 | E15: =IF(AND(C15<>"",D15<>""),IF(D15>=C15,ROUND((D15-C15)*24,2),ROUND((D15-C15+1)*24,2)),"") | F15: =IF(E15<>"",ROUND(E15*$I$2,0),"")
... A34: 7/31 | B34: 金 | E34: =IF(AND(C34<>"",D34<>""),IF(D34>=C34,ROUND((D34-C34)*24,2),ROUND((D34-C34+1)*24,2)),"") | F34: =IF(E34<>"",ROUND(E34*$I$2,0),"")
A36: ■ 月次集計サマリー
A37: 勤務日数 | F37: =COUNT(E4:E34) -> 0
A38: 総勤務時間 | F38: =SUM(E4:E34) -> 0
A39: 給与合計 | F39: =SUM(F4:F34) -> 0
A40: 源泉所得税（乙欄） | F40: =IF(F39=0,0,IFERROR(VLOOKUP(F39,税額表!$A$2:$B$74,2,TRUE()),0)) -> 0
A41: 差引給与（税引後） | F41: =F39-F40 -> 0
A42: 交通費合計 | F42: =SUM(I4:I34) -> 0
A43: 立替金（現金＋個人カード） | F43: =SUMIF(L4:L34,"現金",K4:K34)+SUMIF(L4:L34,"個人カード",K4:K34) -> 0
A44: 送料合計 | F44: =SUM(M4:M34) -> 0
A45: その他経費合計 | F45: =SUM(O4:O34) -> 0
A46: 前月繰越立替金 | F46: ='6月'!F42 -> 0
A47: 総支給額（振込予定額） | F47: =F41+F42+F43+F44+F45+F46 -> 0
A49: 【入力セル凡例】 | C49: 平日入力 | E49: 土曜 | G49: 日曜 | I49: 送料・その他経費 | K49: 前月繰越（自動）
A50: 【注記】① 開始・終了時刻は「9:00」形式で入力 ② 源泉所得税は令和6年分月額表乙欄概算（詳細は国税庁HP参照） ③ 立替金＝現金・個人カード支払いの仕入れ金額合計 ④ 送料・その他経費も総支給額に含まれます ⑤ 前月繰越立替金は前月の立替金を自動参照（1月のみ黄色セルに手入力）

Sheet 8月
A1: 2026年 8月 アルバイト勤怠表
A2: 従業員名 | C2: 仲本 正 | G2: 時 給 | I2: 1300 | L2: （税区分：乙欄 雇用保険なし）
A3: 日 付 | B3: 曜 日 | C3: 勤務 開始時刻 | D3: 勤務 終了時刻 | E3: 勤務時間 (h) | F3: 給与 (円) | G3: 勤務 エリア | H3: 通勤 手段 | I3: 往復 交通費(円) | J3: 仕入れ 店舗 | K3: 仕入れ 合計金額(円) | L3: 支払 方法 | M3: 送料 (円) | N3: その他経費 （内容） | O3: その他経費 （金額円）
A4: 8/1 | B4: 土 | E4: =IF(AND(C4<>"",D4<>""),IF(D4>=C4,ROUND((D4-C4)*24,2),ROUND((D4-C4+1)*24,2)),"") | F4: =IF(E4<>"",ROUND(E4*$I$2,0),"")
A5: 8/2 | B5: 日 | E5: =IF(AND(C5<>"",D5<>""),IF(D5>=C5,ROUND((D5-C5)*24,2),ROUND((D5-C5+1)*24,2)),"") | F5: =IF(E5<>"",ROUND(E5*$I$2,0),"")
A6: 8/3 | B6: 月 | E6: =IF(AND(C6<>"",D6<>""),IF(D6>=C6,ROUND((D6-C6)*24,2),ROUND((D6-C6+1)*24,2)),"") | F6: =IF(E6<>"",ROUND(E6*$I$2,0),"")
A7: 8/4 | B7: 火 | E7: =IF(AND(C7<>"",D7<>""),IF(D7>=C7,ROUND((D7-C7)*24,2),ROUND((D7-C7+1)*24,2)),"") | F7: =IF(E7<>"",ROUND(E7*$I$2,0),"")
A8: 8/5 | B8: 水 | E8: =IF(AND(C8<>"",D8<>""),IF(D8>=C8,ROUND((D8-C8)*24,2),ROUND((D8-C8+1)*24,2)),"") | F8: =IF(E8<>"",ROUND(E8*$I$2,0),"")
A9: 8/6 | B9: 木 | E9: =IF(AND(C9<>"",D9<>""),IF(D9>=C9,ROUND((D9-C9)*24,2),ROUND((D9-C9+1)*24,2)),"") | F9: =IF(E9<>"",ROUND(E9*$I$2,0),"")
A10: 8/7 | B10: 金 | E10: =IF(AND(C10<>"",D10<>""),IF(D10>=C10,ROUND((D10-C10)*24,2),ROUND((D10-C10+1)*24,2)),"") | F10: =IF(E10<>"",ROUND(E10*$I$2,0),"")
A11: 8/8 | B11: 土 | E11: =IF(AND(C11<>"",D11<>""),IF(D11>=C11,ROUND((D11-C11)*24,2),ROUND((D11-C11+1)*24,2)),"") | F11: =IF(E11<>"",ROUND(E11*$I$2,0),"")
A12: 8/9 | B12: 日 | E12: =IF(AND(C12<>"",D12<>""),IF(D12>=C12,ROUND((D12-C12)*24,2),ROUND((D12-C12+1)*24,2)),"") | F12: =IF(E12<>"",ROUND(E12*$I$2,0),"")
A13: 8/10 | B13: 月 | E13: =IF(AND(C13<>"",D13<>""),IF(D13>=C13,ROUND((D13-C13)*24,2),ROUND((D13-C13+1)*24,2)),"") | F13: =IF(E13<>"",ROUND(E13*$I$2,0),"")
A14: 8/11 | B14: 火 | E14: =IF(AND(C14<>"",D14<>""),IF(D14>=C14,ROUND((D14-C14)*24,2),ROUND((D14-C14+1)*24,2)),"") | F14: =IF(E14<>"",ROUND(E14*$I$2,0),"")
A15: 8/12 | B15: 水 | E15: =IF(AND(C15<>"",D15<>""),IF(D15>=C15,ROUND((D15-C15)*24,2),ROUND((D15-C15+1)*24,2)),"") | F15: =IF(E15<>"",ROUND(E15*$I$2,0),"")
... A34: 8/31 | B34: 月 | E34: =IF(AND(C34<>"",D34<>""),IF(D34>=C34,ROUND((D34-C34)*24,2),ROUND((D34-C34+1)*24,2)),"") | F34: =IF(E34<>"",ROUND(E34*$I$2,0),"")
A36: ■ 月次集計サマリー
A37: 勤務日数 | F37: =COUNT(E4:E34) -> 0
A38: 総勤務時間 | F38: =SUM(E4:E34) -> 0
A39: 給与合計 | F39: =SUM(F4:F34) -> 0
A40: 源泉所得税（乙欄） | F40: =IF(F39=0,0,IFERROR(VLOOKUP(F39,税額表!$A$2:$B$74,2,TRUE()),0)) -> 0
A41: 差引給与（税引後） | F41: =F39-F40 -> 0
A42: 交通費合計 | F42: =SUM(I4:I34) -> 0
A43: 立替金（現金＋個人カード） | F43: =SUMIF(L4:L34,"現金",K4:K34)+SUMIF(L4:L34,"個人カード",K4:K34) -> 0
A44: 送料合計 | F44: =SUM(M4:M34) -> 0
A45: その他経費合計 | F45: =SUM(O4:O34) -> 0
A46: 前月繰越立替金 | F46: ='7月'!F43 -> 0
A47: 総支給額（振込予定額） | F47: =F41+F42+F43+F44+F45+F46 -> 0
A49: 【入力セル凡例】 | C49: 平日入力 | E49: 土曜 | G49: 日曜 | I49: 送料・その他経費 | K49: 前月繰越（自動）
A50: 【注記】① 開始・終了時刻は「9:00」形式で入力 ② 源泉所得税は令和6年分月額表乙欄概算（詳細は国税庁HP参照） ③ 立替金＝現金・個人カード支払いの仕入れ金額合計 ④ 送料・その他経費も総支給額に含まれます ⑤ 前月繰越立替金は前月の立替金を自動参照（1月のみ黄色セルに手入力）

Sheet 9月
A1: 2026年 9月 アルバイト勤怠表
A2: 従業員名 | C2: 仲本 正 | G2: 時 給 | I2: 1300 | L2: （税区分：乙欄 雇用保険なし）
A3: 日 付 | B3: 曜 日 | C3: 勤務 開始時刻 | D3: 勤務 終了時刻 | E3: 勤務時間 (h) | F3: 給与 (円) | G3: 勤務 エリア | H3: 通勤 手段 | I3: 往復 交通費(円) | J3: 仕入れ 店舗 | K3: 仕入れ 合計金額(円) | L3: 支払 方法 | M3: 送料 (円) | N3: その他経費 （内容） | O3: その他経費 （金額円）
A4: 9/1 | B4: 火 | E4: =IF(AND(C4<>"",D4<>""),IF(D4>=C4,ROUND((D4-C4)*24,2),ROUND((D4-C4+1)*24,2)),"") | F4: =IF(E4<>"",ROUND(E4*$I$2,0),"")
A5: 9/2 | B5: 水 | E5: =IF(AND(C5<>"",D5<>""),IF(D5>=C5,ROUND((D5-C5)*24,2),ROUND((D5-C5+1)*24,2)),"") | F5: =IF(E5<>"",ROUND(E5*$I$2,0),"")
A6: 9/3 | B6: 木 | E6: =IF(AND(C6<>"",D6<>""),IF(D6>=C6,ROUND((D6-C6)*24,2),ROUND((D6-C6+1)*24,2)),"") | F6: =IF(E6<>"",ROUND(E6*$I$2,0),"")
A7: 9/4 | B7: 金 | E7: =IF(AND(C7<>"",D7<>""),IF(D7>=C7,ROUND((D7-C7)*24,2),ROUND((D7-C7+1)*24,2)),"") | F7: =IF(E7<>"",ROUND(E7*$I$2,0),"")
A8: 9/5 | B8: 土 | E8: =IF(AND(C8<>"",D8<>""),IF(D8>=C8,ROUND((D8-C8)*24,2),ROUND((D8-C8+1)*24,2)),"") | F8: =IF(E8<>"",ROUND(E8*$I$2,0),"")
A9: 9/6 | B9: 日 | E9: =IF(AND(C9<>"",D9<>""),IF(D9>=C9,ROUND((D9-C9)*24,2),ROUND((D9-C9+1)*24,2)),"") | F9: =IF(E9<>"",ROUND(E9*$I$2,0),"")
A10: 9/7 | B10: 月 | E10: =IF(AND(C10<>"",D10<>""),IF(D10>=C10,ROUND((D10-C10)*24,2),ROUND((D10-C10+1)*24,2)),"") | F10: =IF(E10<>"",ROUND(E10*$I$2,0),"")
A11: 9/8 | B11: 火 | E11: =IF(AND(C11<>"",D11<>""),IF(D11>=C11,ROUND((D11-C11)*24,2),ROUND((D11-C11+1)*24,2)),"") | F11: =IF(E11<>"",ROUND(E11*$I$2,0),"")
A12: 9/9 | B12: 水 | E12: =IF(AND(C12<>"",D12<>""),IF(D12>=C12,ROUND((D12-C12)*24,2),ROUND((D12-C12+1)*24,2)),"") | F12: =IF(E12<>"",ROUND(E12*$I$2,0),"")
A13: 9/10 | B13: 木 | E13: =IF(AND(C13<>"",D13<>""),IF(D13>=C13,ROUND((D13-C13)*24,2),ROUND((D13-C13+1)*24,2)),"") | F13: =IF(E13<>"",ROUND(E13*$I$2,0),"")
A14: 9/11 | B14: 金 | E14: =IF(AND(C14<>"",D14<>""),IF(D14>=C14,ROUND((D14-C14)*24,2),ROUND((D14-C14+1)*24,2)),"") | F14: =IF(E14<>"",ROUND(E14*$I$2,0),"")
A15: 9/12 | B15: 土 | E15: =IF(AND(C15<>"",D15<>""),IF(D15>=C15,ROUND((D15-C15)*24,2),ROUND((D15-C15+1)*24,2)),"") | F15: =IF(E15<>"",ROUND(E15*$I$2,0),"")
... A33: 9/30 | B33: 水 | E33: =IF(AND(C33<>"",D33<>""),IF(D33>=C33,ROUND((D33-C33)*24,2),ROUND((D33-C33+1)*24,2)),"") | F33: =IF(E33<>"",ROUND(E33*$I$2,0),"")
A35: ■ 月次集計サマリー
A36: 勤務日数 | F36: =COUNT(E4:E33) -> 0
A37: 総勤務時間 | F37: =SUM(E4:E33) -> 0
A38: 給与合計 | F38: =SUM(F4:F33) -> 0
A39: 源泉所得税（乙欄） | F39: =IF(F38=0,0,IFERROR(VLOOKUP(F38,税額表!$A$2:$B$74,2,TRUE()),0)) -> 0
A40: 差引給与（税引後） | F40: =F38-F39 -> 0
A41: 交通費合計 | F41: =SUM(I4:I33) -> 0
A42: 立替金（現金＋個人カード） | F42: =SUMIF(L4:L33,"現金",K4:K33)+SUMIF(L4:L33,"個人カード",K4:K33) -> 0
A43: 送料合計 | F43: =SUM(M4:M33) -> 0
A44: その他経費合計 | F44: =SUM(O4:O33) -> 0
A45: 前月繰越立替金 | F45: ='8月'!F43 -> 0
A46: 総支給額（振込予定額） | F46: =F40+F41+F42+F43+F44+F45 -> 0
A48: 【入力セル凡例】 | C48: 平日入力 | E48: 土曜 | G48: 日曜 | I48: 送料・その他経費 | K48: 前月繰越（自動）
A49: 【注記】① 開始・終了時刻は「9:00」形式で入力 ② 源泉所得税は令和6年分月額表乙欄概算（詳細は国税庁HP参照） ③ 立替金＝現金・個人カード支払いの仕入れ金額合計 ④ 送料・その他経費も総支給額に含まれます ⑤ 前月繰越立替金は前月の立替金を自動参照（1月のみ黄色セルに手入力）

Sheet 10月
A1: 2026年 10月 アルバイト勤怠表
A2: 従業員名 | C2: 仲本 正 | G2: 時 給 | I2: 1300 | L2: （税区分：乙欄 雇用保険なし）
A3: 日 付 | B3: 曜 日 | C3: 勤務 開始時刻 | D3: 勤務 終了時刻 | E3: 勤務時間 (h) | F3: 給与 (円) | G3: 勤務 エリア | H3: 通勤 手段 | I3: 往復 交通費(円) | J3: 仕入れ 店舗 | K3: 仕入れ 合計金額(円) | L3: 支払 方法 | M3: 送料 (円) | N3: その他経費 （内容） | O3: その他経費 （金額円）
A4: 10/1 | B4: 木 | E4: =IF(AND(C4<>"",D4<>""),IF(D4>=C4,ROUND((D4-C4)*24,2),ROUND((D4-C4+1)*24,2)),"") | F4: =IF(E4<>"",ROUND(E4*$I$2,0),"")
A5: 10/2 | B5: 金 | E5: =IF(AND(C5<>"",D5<>""),IF(D5>=C5,ROUND((D5-C5)*24,2),ROUND((D5-C5+1)*24,2)),"") | F5: =IF(E5<>"",ROUND(E5*$I$2,0),"")
A6: 10/3 | B6: 土 | E6: =IF(AND(C6<>"",D6<>""),IF(D6>=C6,ROUND((D6-C6)*24,2),ROUND((D6-C6+1)*24,2)),"") | F6: =IF(E6<>"",ROUND(E6*$I$2,0),"")
A7: 10/4 | B7: 日 | E7: =IF(AND(C7<>"",D7<>""),IF(D7>=C7,ROUND((D7-C7)*24,2),ROUND((D7-C7+1)*24,2)),"") | F7: =IF(E7<>"",ROUND(E7*$I$2,0),"")
A8: 10/5 | B8: 月 | E8: =IF(AND(C8<>"",D8<>""),IF(D8>=C8,ROUND((D8-C8)*24,2),ROUND((D8-C8+1)*24,2)),"") | F8: =IF(E8<>"",ROUND(E8*$I$2,0),"")
A9: 10/6 | B9: 火 | E9: =IF(AND(C9<>"",D9<>""),IF(D9>=C9,ROUND((D9-C9)*24,2),ROUND((D9-C9+1)*24,2)),"") | F9: =IF(E9<>"",ROUND(E9*$I$2,0),"")
A10: 10/7 | B10: 水 | E10: =IF(AND(C10<>"",D10<>""),IF(D10>=C10,ROUND((D10-C10)*24,2),ROUND((D10-C10+1)*24,2)),"") | F10: =IF(E10<>"",ROUND(E10*$I$2,0),"")
A11: 10/8 | B11: 木 | E11: =IF(AND(C11<>"",D11<>""),IF(D11>=C11,ROUND((D11-C11)*24,2),ROUND((D11-C11+1)*24,2)),"") | F11: =IF(E11<>"",ROUND(E11*$I$2,0),"")
A12: 10/9 | B12: 金 | E12: =IF(AND(C12<>"",D12<>""),IF(D12>=C12,ROUND((D12-C12)*24,2),ROUND((D12-C12+1)*24,2)),"") | F12: =IF(E12<>"",ROUND(E12*$I$2,0),"")
A13: 10/10 | B13: 土 | E13: =IF(AND(C13<>"",D13<>""),IF(D13>=C13,ROUND((D13-C13)*24,2),ROUND((D13-C13+1)*24,2)),"") | F13: =IF(E13<>"",ROUND(E13*$I$2,0),"")
A14: 10/11 | B14: 日 | E14: =IF(AND(C14<>"",D14<>""),IF(D14>=C14,ROUND((D14-C14)*24,2),ROUND((D14-C14+1)*24,2)),"") | F14: =IF(E14<>"",ROUND(E14*$I$2,0),"")
A15: 10/12 | B15: 月 | E15: =IF(AND(C15<>"",D15<>""),IF(D15>=C15,ROUND((D15-C15)*24,2),ROUND((D15-C15+1)*24,2)),"") | F15: =IF(E15<>"",ROUND(E15*$I$2,0),"")
... A34: 10/31 | B34: 土 | E34: =IF(AND(C34<>"",D34<>""),IF(D34>=C34,ROUND((D34-C34)*24,2),ROUND((D34-C34+1)*24,2)),"") | F34: =IF(E34<>"",ROUND(E34*$I$2,0),"")
A36: ■ 月次集計サマリー
A37: 勤務日数 | F37: =COUNT(E4:E34) -> 0
A38: 総勤務時間 | F38: =SUM(E4:E34) -> 0
A39: 給与合計 | F39: =SUM(F4:F34) -> 0
A40: 源泉所得税（乙欄） | F40: =IF(F39=0,0,IFERROR(VLOOKUP(F39,税額表!$A$2:$B$74,2,TRUE()),0)) -> 0
A41: 差引給与（税引後） | F41: =F39-F40 -> 0
A42: 交通費合計 | F42: =SUM(I4:I34) -> 0
A43: 立替金（現金＋個人カード） | F43: =SUMIF(L4:L34,"現金",K4:K34)+SUMIF(L4:L34,"個人カード",K4:K34) -> 0
A44: 送料合計 | F44: =SUM(M4:M34) -> 0
A45: その他経費合計 | F45: =SUM(O4:O34) -> 0
A46: 前月繰越立替金 | F46: ='9月'!F42 -> 0
A47: 総支給額（振込予定額） | F47: =F41+F42+F43+F44+F45+F46 -> 0
A49: 【入力セル凡例】 | C49: 平日入力 | E49: 土曜 | G49: 日曜 | I49: 送料・その他経費 | K49: 前月繰越（自動）
A50: 【注記】① 開始・終了時刻は「9:00」形式で入力 ② 源泉所得税は令和6年分月額表乙欄概算（詳細は国税庁HP参照） ③ 立替金＝現金・個人カード支払いの仕入れ金額合計 ④ 送料・その他経費も総支給額に含まれます ⑤ 前月繰越立替金は前月の立替金を自動参照（1月のみ黄色セルに手入力）

Sheet 11月
A1: 2026年 11月 アルバイト勤怠表
A2: 従業員名 | C2: 仲本 正 | G2: 時 給 | I2: 1300 | L2: （税区分：乙欄 雇用保険なし）
A3: 日 付 | B3: 曜 日 | C3: 勤務 開始時刻 | D3: 勤務 終了時刻 | E3: 勤務時間 (h) | F3: 給与 (円) | G3: 勤務 エリア | H3: 通勤 手段 | I3: 往復 交通費(円) | J3: 仕入れ 店舗 | K3: 仕入れ 合計金額(円) | L3: 支払 方法 | M3: 送料 (円) | N3: その他経費 （内容） | O3: その他経費 （金額円）
A4: 11/1 | B4: 日 | E4: =IF(AND(C4<>"",D4<>""),IF(D4>=C4,ROUND((D4-C4)*24,2),ROUND((D4-C4+1)*24,2)),"") | F4: =IF(E4<>"",ROUND(E4*$I$2,0),"")
A5: 11/2 | B5: 月 | E5: =IF(AND(C5<>"",D5<>""),IF(D5>=C5,ROUND((D5-C5)*24,2),ROUND((D5-C5+1)*24,2)),"") | F5: =IF(E5<>"",ROUND(E5*$I$2,0),"")
A6: 11/3 | B6: 火 | E6: =IF(AND(C6<>"",D6<>""),IF(D6>=C6,ROUND((D6-C6)*24,2),ROUND((D6-C6+1)*24,2)),"") | F6: =IF(E6<>"",ROUND(E6*$I$2,0),"")
A7: 11/4 | B7: 水 | E7: =IF(AND(C7<>"",D7<>""),IF(D7>=C7,ROUND((D7-C7)*24,2),ROUND((D7-C7+1)*24,2)),"") | F7: =IF(E7<>"",ROUND(E7*$I$2,0),"")
A8: 11/5 | B8: 木 | E8: =IF(AND(C8<>"",D8<>""),IF(D8>=C8,ROUND((D8-C8)*24,2),ROUND((D8-C8+1)*24,2)),"") | F8: =IF(E8<>"",ROUND(E8*$I$2,0),"")
A9: 11/6 | B9: 金 | E9: =IF(AND(C9<>"",D9<>""),IF(D9>=C9,ROUND((D9-C9)*24,2),ROUND((D9-C9+1)*24,2)),"") | F9: =IF(E9<>"",ROUND(E9*$I$2,0),"")
A10: 11/7 | B10: 土 | E10: =IF(AND(C10<>"",D10<>""),IF(D10>=C10,ROUND((D10-C10)*24,2),ROUND((D10-C10+1)*24,2)),"") | F10: =IF(E10<>"",ROUND(E10*$I$2,0),"")
A11: 11/8 | B11: 日 | E11: =IF(AND(C11<>"",D11<>""),IF(D11>=C11,ROUND((D11-C11)*24,2),ROUND((D11-C11+1)*24,2)),"") | F11: =IF(E11<>"",ROUND(E11*$I$2,0),"")
A12: 11/9 | B12: 月 | E12: =IF(AND(C12<>"",D12<>""),IF(D12>=C12,ROUND((D12-C12)*24,2),ROUND((D12-C12+1)*24,2)),"") | F12: =IF(E12<>"",ROUND(E12*$I$2,0),"")
A13: 11/10 | B13: 火 | E13: =IF(AND(C13<>"",D13<>""),IF(D13>=C13,ROUND((D13-C13)*24,2),ROUND((D13-C13+1)*24,2)),"") | F13: =IF(E13<>"",ROUND(E13*$I$2,0),"")
A14: 11/11 | B14: 水 | E14: =IF(AND(C14<>"",D14<>""),IF(D14>=C14,ROUND((D14-C14)*24,2),ROUND((D14-C14+1)*24,2)),"") | F14: =IF(E14<>"",ROUND(E14*$I$2,0),"")
A15: 11/12 | B15: 木 | E15: =IF(AND(C15<>"",D15<>""),IF(D15>=C15,ROUND((D15-C15)*24,2),ROUND((D15-C15+1)*24,2)),"") | F15: =IF(E15<>"",ROUND(E15*$I$2,0),"")
... A33: 11/30 | B33: 月 | E33: =IF(AND(C33<>"",D33<>""),IF(D33>=C33,ROUND((D33-C33)*24,2),ROUND((D33-C33+1)*24,2)),"") | F33: =IF(E33<>"",ROUND(E33*$I$2,0),"")
A35: ■ 月次集計サマリー
A36: 勤務日数 | F36: =COUNT(E4:E33) -> 0
A37: 総勤務時間 | F37: =SUM(E4:E33) -> 0
A38: 給与合計 | F38: =SUM(F4:F33) -> 0
A39: 源泉所得税（乙欄） | F39: =IF(F38=0,0,IFERROR(VLOOKUP(F38,税額表!$A$2:$B$74,2,TRUE()),0)) -> 0
A40: 差引給与（税引後） | F40: =F38-F39 -> 0
A41: 交通費合計 | F41: =SUM(I4:I33) -> 0
A42: 立替金（現金＋個人カード） | F42: =SUMIF(L4:L33,"現金",K4:K33)+SUMIF(L4:L33,"個人カード",K4:K33) -> 0
A43: 送料合計 | F43: =SUM(M4:M33) -> 0
A44: その他経費合計 | F44: =SUM(O4:O33) -> 0
A45: 前月繰越立替金 | F45: ='10月'!F43 -> 0
A46: 総支給額（振込予定額） | F46: =F40+F41+F42+F43+F44+F45 -> 0
A48: 【入力セル凡例】 | C48: 平日入力 | E48: 土曜 | G48: 日曜 | I48: 送料・その他経費 | K48: 前月繰越（自動）
A49: 【注記】① 開始・終了時刻は「9:00」形式で入力 ② 源泉所得税は令和6年分月額表乙欄概算（詳細は国税庁HP参照） ③ 立替金＝現金・個人カード支払いの仕入れ金額合計 ④ 送料・その他経費も総支給額に含まれます ⑤ 前月繰越立替金は前月の立替金を自動参照（1月のみ黄色セルに手入力）

Sheet 12月
A1: 2026年 12月 アルバイト勤怠表
A2: 従業員名 | C2: 仲本 正 | G2: 時 給 | I2: 1300 | L2: （税区分：乙欄 雇用保険なし）
A3: 日 付 | B3: 曜 日 | C3: 勤務 開始時刻 | D3: 勤務 終了時刻 | E3: 勤務時間 (h) | F3: 給与 (円) | G3: 勤務 エリア | H3: 通勤 手段 | I3: 往復 交通費(円) | J3: 仕入れ 店舗 | K3: 仕入れ 合計金額(円) | L3: 支払 方法 | M3: 送料 (円) | N3: その他経費 （内容） | O3: その他経費 （金額円）
A4: 12/1 | B4: 火 | E4: =IF(AND(C4<>"",D4<>""),IF(D4>=C4,ROUND((D4-C4)*24,2),ROUND((D4-C4+1)*24,2)),"") | F4: =IF(E4<>"",ROUND(E4*$I$2,0),"")
A5: 12/2 | B5: 水 | E5: =IF(AND(C5<>"",D5<>""),IF(D5>=C5,ROUND((D5-C5)*24,2),ROUND((D5-C5+1)*24,2)),"") | F5: =IF(E5<>"",ROUND(E5*$I$2,0),"")
A6: 12/3 | B6: 木 | E6: =IF(AND(C6<>"",D6<>""),IF(D6>=C6,ROUND((D6-C6)*24,2),ROUND((D6-C6+1)*24,2)),"") | F6: =IF(E6<>"",ROUND(E6*$I$2,0),"")
A7: 12/4 | B7: 金 | E7: =IF(AND(C7<>"",D7<>""),IF(D7>=C7,ROUND((D7-C7)*24,2),ROUND((D7-C7+1)*24,2)),"") | F7: =IF(E7<>"",ROUND(E7*$I$2,0),"")
A8: 12/5 | B8: 土 | E8: =IF(AND(C8<>"",D8<>""),IF(D8>=C8,ROUND((D8-C8)*24,2),ROUND((D8-C8+1)*24,2)),"") | F8: =IF(E8<>"",ROUND(E8*$I$2,0),"")
A9: 12/6 | B9: 日 | E9: =IF(AND(C9<>"",D9<>""),IF(D9>=C9,ROUND((D9-C9)*24,2),ROUND((D9-C9+1)*24,2)),"") | F9: =IF(E9<>"",ROUND(E9*$I$2,0),"")
A10: 12/7 | B10: 月 | E10: =IF(AND(C10<>"",D10<>""),IF(D10>=C10,ROUND((D10-C10)*24,2),ROUND((D10-C10+1)*24,2)),"") | F10: =IF(E10<>"",ROUND(E10*$I$2,0),"")
A11: 12/8 | B11: 火 | E11: =IF(AND(C11<>"",D11<>""),IF(D11>=C11,ROUND((D11-C11)*24,2),ROUND((D11-C11+1)*24,2)),"") | F11: =IF(E11<>"",ROUND(E11*$I$2,0),"")
A12: 12/9 | B12: 水 | E12: =IF(AND(C12<>"",D12<>""),IF(D12>=C12,ROUND((D12-C12)*24,2),ROUND((D12-C12+1)*24,2)),"") | F12: =IF(E12<>"",ROUND(E12*$I$2,0),"")
A13: 12/10 | B13: 木 | E13: =IF(AND(C13<>"",D13<>""),IF(D13>=C13,ROUND((D13-C13)*24,2),ROUND((D13-C13+1)*24,2)),"") | F13: =IF(E13<>"",ROUND(E13*$I$2,0),"")
A14: 12/11 | B14: 金 | E14: =IF(AND(C14<>"",D14<>""),IF(D14>=C14,ROUND((D14-C14)*24,2),ROUND((D14-C14+1)*24,2)),"") | F14: =IF(E14<>"",ROUND(E14*$I$2,0),"")
A15: 12/12 | B15: 土 | E15: =IF(AND(C15<>"",D15<>""),IF(D15>=C15,ROUND((D15-C15)*24,2),ROUND((D15-C15+1)*24,2)),"") | F15: =IF(E15<>"",ROUND(E15*$I$2,0),"")
... A34: 12/31 | B34: 木 | E34: =IF(AND(C34<>"",D34<>""),IF(D34>=C34,ROUND((D34-C34)*24,2),ROUND((D34-C34+1)*24,2)),"") | F34: =IF(E34<>"",ROUND(E34*$I$2,0),"")
A36: ■ 月次集計サマリー
A37: 勤務日数 | F37: =COUNT(E4:E34) -> 0
A38: 総勤務時間 | F38: =SUM(E4:E34) -> 0
A39: 給与合計 | F39: =SUM(F4:F34) -> 0
A40: 源泉所得税（乙欄） | F40: =IF(F39=0,0,IFERROR(VLOOKUP(F39,税額表!$A$2:$B$74,2,TRUE()),0)) -> 0
A41: 差引給与（税引後） | F41: =F39-F40 -> 0
A42: 交通費合計 | F42: =SUM(I4:I34) -> 0
A43: 立替金（現金＋個人カード） | F43: =SUMIF(L4:L34,"現金",K4:K34)+SUMIF(L4:L34,"個人カード",K4:K34) -> 0
A44: 送料合計 | F44: =SUM(M4:M34) -> 0
A45: その他経費合計 | F45: =SUM(O4:O34) -> 0
A46: 前月繰越立替金 | F46: ='11月'!F42 -> 0
A47: 総支給額（振込予定額） | F47: =F41+F42+F43+F44+F45+F46 -> 0
A49: 【入力セル凡例】 | C49: 平日入力 | E49: 土曜 | G49: 日曜 | I49: 送料・その他経費 | K49: 前月繰越（自動）
A50: 【注記】① 開始・終了時刻は「9:00」形式で入力 ② 源泉所得税は令和6年分月額表乙欄概算（詳細は国税庁HP参照） ③ 立替金＝現金・個人カード支払いの仕入れ金額合計 ④ 送料・その他経費も総支給額に含まれます ⑤ 前月繰越立替金は前月の立替金を自動参照（1月のみ黄色セルに手入力）
